README.md
setup.py
auth_jwt/__init__.py
auth_jwt/application.py
auth_jwt/helpers.py
auth_jwt.egg-info/PKG-INFO
auth_jwt.egg-info/SOURCES.txt
auth_jwt.egg-info/dependency_links.txt
auth_jwt.egg-info/not-zip-safe
auth_jwt.egg-info/requires.txt
auth_jwt.egg-info/top_level.txt