Metadata-Version: 1.0
Name: auth-jwt
Version: 0.1.9
Summary: Module to give secure the api with jwt token
Home-page: https://github.com/handersonc/auth_jwt.git
Author: Handerson Contreras
Author-email: handerson.contreras@gmail.com
License: MIT
Platform: UNKNOWN
